AUTHORS.md
CHANGELOG.md
LICENSE
MANIFEST.in
README.md
pyproject.toml
setup.py
src/crashd/__init__.py
src/crashd/asan/__init__.py
src/crashd/asan/asan.py
src/crashd/dwarf/__init__.py
src/crashd/dwarf/dwarf_data.py
src/crashd/dwarf/dwarf_source_code.py
src/crashd/dwarf/template.html
src/crashd/static_analysis/__init__.py
src/crashd/static_analysis/ida_plugin.py
src/crashd/static_analysis/ida_server.py
src/crashd/taint/__init__.py
src/crashd/taint/taint.py
src/crashd/taint/taint_graph.py
src/crashd/taint/tcg.py
src/crashd/taint/render/__init__.py
src/crashd/taint/render/graphviz.py
src/crashd/taint/render/ida.py
src/zelos_crashd.egg-info/PKG-INFO
src/zelos_crashd.egg-info/SOURCES.txt
src/zelos_crashd.egg-info/dependency_links.txt
src/zelos_crashd.egg-info/entry_points.txt
src/zelos_crashd.egg-info/not-zip-safe
src/zelos_crashd.egg-info/requires.txt
src/zelos_crashd.egg-info/top_level.txt