Metadata-Version: 2.1
Name: zelos-crashd
Version: 0.0.1
Summary: A zelos plugin for crash analysis.
Home-page: https://github.com/zeropointdynamics/zelos-crashd
Author: Zeropoint Dynamics
Author-email: zelos@zeropointdynamics.com
Maintainer: Zeropoint Dynamics
Maintainer-email: zelos@zeropointdynamics.com
License: AGPLv3
Project-URL: Bug Tracker, https://github.com/zeropointdynamics/zelos-crashd/issues
Project-URL: Source Code, https://github.com/zeropointdynamics/zelos-crashd
Keywords: emulation,dynamic analysis,binary analysis,zelos,crash,vulnerability assessment
Platform: UNKNOWN
Classifier: Development Status :: 4 - Beta
Classifier: Natural Language :: English
Classifier: License :: OSI Approved :: GNU Affero General Public License v3
Classifier: Operating System :: OS Independent
Classifier: Programming Language :: Python
Classifier: Programming Language :: Python :: 3
Classifier: Programming Language :: Python :: 3.6
Classifier: Programming Language :: Python :: 3.7
Classifier: Programming Language :: Python :: 3.8
Requires-Python: >=3.6.0
